{
    "products": [
        {
            "id": 1001,
            "title": "Cat Food, 25lb bag",
            "description": "A 25 pound bag of <em>irresistable</em>, organic goodness for your cat.",
            "price": 3599,
            "image": "img/products/cat_food.jpg",
            "availableInventory": 10,
            "rating": 3
        },
        {
            "id": 1002,
            "title": "Yarn",
            "description": "Yarn your cat can play with for a very <strong>long</strong> time!",
            "price": 499,
            "image": "img/products/yarn.jpg",
            "availableInventory": 7,
            "rating": 1
        },
        {
            "id": 1003,
            "title": "Kitty litter",
            "description": "Premium kitty litter for your cat.",
            "price": 4999,
            "image": "img/products/cat_litter.png",
            "availableInventory": 99,
            "rating": 4
        },
        {
            "id": 1004,
            "title": "Cat House",
            "description": "A place for your cat to play!",
            "price": 14999,
            "image": "img/products/cat_house.jpg",
            "availableInventory": 11,
            "rating": 5
        },
        {
            "id": 1005,
            "title": "Laser pointer",
            "description": "foukin layser sights",
            "price": 299,
            "image": "img/products/laser.jpg",
            "availableInventory": 25,
            "rating": 1
        }
    ]
}